csc3730TaxisProjectZhou/__init__.py
csc3730TaxisProjectZhou/taxiDataAnalysis.py
csc3730TaxisProjectZhou-0.0.1.dist-info/METADATA
csc3730TaxisProjectZhou-0.0.1.dist-info/WHEEL
csc3730TaxisProjectZhou-0.0.1.dist-info/top_level.txt
csc3730TaxisProjectZhou-0.0.1.dist-info/RECORD
