Metadata-Version: 2.1
Name: csc3730TaxisProjectZhou
Version: 0.0.1
Summary: NYC taxi dataset analysis
Author: Author
Classifier: Programming Language :: Python :: 3
Classifier: License :: OSI Approved :: MIT License
Classifier: Operating System :: OS Independent
Requires-Python: >=3.7
